{
  "openapi": "3.0.1",
  "info": {
    "title": "_8_SourceGenerators.WebApi",
    "version": "v1"
  },
  "paths": {
    "/WeatherForecast": {
      "get": {
        "tags": [
          "WeatherForecast"
        ],
        "responses": {
          "200": {
            "description": "Success",
            "content": {
              "text/plain": {
                "schema": {
                  "$ref": "#/components/schemas/WeatherForecast"
                }
              },
              "application/json": {
                "schema": {
                  "$ref": "#/components/schemas/WeatherForecast"
                }
              },
              "text/json": {
                "schema": {
                  "$ref": "#/components/schemas/WeatherForecast"
                }
              }
            }
          }
        }
      }
    }
  },
  "components": {
    "schemas": {
      "WeatherForecast": {
        "type": "object",
        "properties": {
          "date": {
            "type": "string",
            "format": "date-time"
          },
          "temperature": {
            "type": "integer",
            "format": "int32"
          },
          "summary": {
            "type": "string",
            "nullable": true
          }
        },
        "additionalProperties": false
      }
    }
  }
}